{"pageContext":{"isCreatedByStatefulCreatePages":false,"electionName":"2016 Legislator Election","regionName":"苗栗縣","constituenciesOfRegion":[{"name":"第01選區","candidates":[{"name":"杜文卿","partyName":"民主進步黨","isElected":false,"rateOfVote":35.86,"finance":null},{"name":"康世儒","partyName":"民國黨","isElected":false,"rateOfVote":17.34,"finance":null},{"name":"黃玉燕","partyName":"無黨籍及未經政黨推薦","isElected":false,"rateOfVote":2.3,"finance":null},{"name":"陳超明","partyName":"中國國民黨","isElected":true,"rateOfVote":42.26,"finance":{"income":{"total":29502803},"outcome":{"total":29701445}}},{"name":"林一方","partyName":"自由台灣黨","isElected":false,"rateOfVote":2.23,"finance":null}]},{"name":"第02選區","candidates":[{"name":"戴文祥","partyName":"無黨籍及未經政黨推薦","isElected":false,"rateOfVote":2.09,"finance":null},{"name":"徐志榮","partyName":"中國國民黨","isElected":true,"rateOfVote":49.9,"finance":{"income":{"total":13313980},"outcome":{"total":18291802}}},{"name":"周書涵","partyName":"無黨籍及未經政黨推薦","isElected":false,"rateOfVote":3.04,"finance":null},{"name":"吳宜臻","partyName":"民主進步黨","isElected":false,"rateOfVote":44.6,"finance":null},{"name":"劉文忠","partyName":"自由台灣黨","isElected":false,"rateOfVote":0.35,"finance":null}]}],"constituency":{"name":"第01選區","candidates":[{"name":"杜文卿","partyName":"民主進步黨","isElected":false,"rateOfVote":35.86,"finance":null},{"name":"康世儒","partyName":"民國黨","isElected":false,"rateOfVote":17.34,"finance":null},{"name":"黃玉燕","partyName":"無黨籍及未經政黨推薦","isElected":false,"rateOfVote":2.3,"finance":null},{"name":"陳超明","partyName":"中國國民黨","isElected":true,"rateOfVote":42.26,"finance":{"income":{"total":29502803},"outcome":{"total":29701445}}},{"name":"林一方","partyName":"自由台灣黨","isElected":false,"rateOfVote":2.23,"finance":null}]}}}