{"pageContext":{"isCreatedByStatefulCreatePages":false,"electionName":"2016 Legislator Election","regionName":"新北市","constituenciesOfRegion":[{"name":"第01選區","candidates":[{"name":"吳育昇","partyName":"中國國民黨","isElected":false,"rateOfVote":40.87,"finance":null},{"name":"蘇通達","partyName":"樹黨","isElected":false,"rateOfVote":2.47,"finance":null},{"name":"洪志成","partyName":"健保免費連線","isElected":false,"rateOfVote":0.66,"finance":null},{"name":"呂孫綾","partyName":"民主進步黨","isElected":true,"rateOfVote":53.27,"finance":{"income":{"total":782640},"outcome":{"total":7740367}}},{"name":"陳立基","partyName":"無黨籍及未經政黨推薦","isElected":false,"rateOfVote":2.35,"finance":null},{"name":"陳筠棻","partyName":"和平鴿聯盟黨","isElected":false,"rateOfVote":0.35,"finance":null}]},{"name":"第02選區","candidates":[{"name":"陳明義","partyName":"中國國民黨","isElected":false,"rateOfVote":31.25,"finance":null},{"name":"林淑芬","partyName":"民主進步黨","isElected":true,"rateOfVote":68.74,"finance":{"income":{"total":16525720},"outcome":{"total":15498915}}}]},{"name":"第03選區","candidates":[{"name":"陳長發","partyName":"大愛憲改聯盟","isElected":false,"rateOfVote":0.36,"finance":null},{"name":"蕭忠漢","partyName":"健保免費連線","isElected":false,"rateOfVote":0.3,"finance":null},{"name":"李乾龍","partyName":"中國國民黨","isElected":false,"rateOfVote":35.43,"finance":null},{"name":"高志鵬","partyName":"民主進步黨","isElected":true,"rateOfVote":54.54,"finance":{"income":{"total":28658947},"outcome":{"total":20357048}}},{"name":"張碩文","partyName":"親民黨","isElected":false,"rateOfVote":7.55,"finance":null},{"name":"林其瑩","partyName":"社會福利黨","isElected":false,"rateOfVote":0.62,"finance":null},{"name":"姚胤宏","partyName":"樹黨","isElected":false,"rateOfVote":0.74,"finance":null},{"name":"黃茂","partyName":"無黨籍及未經政黨推薦","isElected":false,"rateOfVote":0.17,"finance":null},{"name":"蘇卿彥","partyName":"無黨籍及未經政黨推薦","isElected":false,"rateOfVote":0.24,"finance":null}]},{"name":"第04選區","candidates":[{"name":"賈伯楷","partyName":"綠黨社會民主黨聯盟","isElected":false,"rateOfVote":4.64,"finance":null},{"name":"吳秉叡","partyName":"民主進步黨","isElected":true,"rateOfVote":62.98,"finance":{"income":{"total":50205014},"outcome":{"total":29187360}}},{"name":"王斯儀","partyName":"大愛憲改聯盟","isElected":false,"rateOfVote":1.54,"finance":null},{"name":"陳茂嘉","partyName":"中國國民黨","isElected":false,"rateOfVote":29.4,"finance":null},{"name":"劉鳳章","partyName":"和平鴿聯盟黨","isElected":false,"rateOfVote":0.27,"finance":null},{"name":"林麗容","partyName":"正黨","isElected":false,"rateOfVote":0.45,"finance":null},{"name":"邱鴻玕","partyName":"無黨籍及未經政黨推薦","isElected":false,"rateOfVote":0.68,"finance":null}]},{"name":"第05選區","candidates":[{"name":"蘇巧慧","partyName":"民主進步黨","isElected":true,"rateOfVote":56.11,"finance":{"income":{"total":20398298},"outcome":{"total":28176988}}},{"name":"郭柏瑜","partyName":"時代力量","isElected":false,"rateOfVote":3.12,"finance":null},{"name":"黃志雄","partyName":"中國國民黨","isElected":false,"rateOfVote":40.76,"finance":null}]},{"name":"第06選區","candidates":[{"name":"姚玉霜","partyName":"台灣工黨","isElected":false,"rateOfVote":0.52,"finance":null},{"name":"李建明","partyName":"樹黨","isElected":false,"rateOfVote":1.23,"finance":null},{"name":"游信義","partyName":"信心希望聯盟","isElected":false,"rateOfVote":1.78,"finance":null},{"name":"康仁俊","partyName":"親民黨","isElected":false,"rateOfVote":2.78,"finance":null},{"name":"莊豐銘","partyName":"無黨籍及未經政黨推薦","isElected":false,"rateOfVote":0.69,"finance":null},{"name":"李貴寶","partyName":"民國黨","isElected":false,"rateOfVote":0.48,"finance":null},{"name":"黃鈞民","partyName":"軍公教聯盟黨","isElected":false,"rateOfVote":0.32,"finance":null},{"name":"林國春","partyName":"中國國民黨","isElected":false,"rateOfVote":39.55,"finance":null},{"name":"張宏陸","partyName":"民主進步黨","isElected":true,"rateOfVote":52.61,"finance":{"income":{"total":9849551},"outcome":{"total":9898185}}}]},{"name":"第07選區","candidates":[{"name":"汪成華","partyName":"健保免費連線","isElected":false,"rateOfVote":1.32,"finance":null},{"name":"羅致政","partyName":"民主進步黨","isElected":true,"rateOfVote":53.61,"finance":{"income":{"total":27091601},"outcome":{"total":25521030}}},{"name":"李婉鈺","partyName":"無黨籍及未經政黨推薦","isElected":false,"rateOfVote":5.22,"finance":null},{"name":"江惠貞","partyName":"中國國民黨","isElected":false,"rateOfVote":39.84,"finance":null}]},{"name":"第08選區","candidates":[{"name":"江永昌","partyName":"民主進步黨","isElected":true,"rateOfVote":53.66,"finance":{"income":{"total":10074838},"outcome":{"total":14931651}}},{"name":"張慶忠","partyName":"中國國民黨","isElected":false,"rateOfVote":40.42,"finance":null},{"name":"童正億","partyName":"無黨籍及未經政黨推薦","isElected":false,"rateOfVote":3.91,"finance":null},{"name":"吳金魁","partyName":"軍公教聯盟黨","isElected":false,"rateOfVote":0.85,"finance":null},{"name":"林建志","partyName":"健保免費連線","isElected":false,"rateOfVote":0.7,"finance":null},{"name":"邵伯祥","partyName":"大愛憲改聯盟","isElected":false,"rateOfVote":0.43,"finance":null}]},{"name":"第09選區","candidates":[{"name":"董建一","partyName":"中華民國機車黨","isElected":false,"rateOfVote":1.92,"finance":null},{"name":"張菁芳","partyName":"民國黨","isElected":false,"rateOfVote":15.05,"finance":null},{"name":"曾文聖","partyName":"健保免費連線","isElected":false,"rateOfVote":1,"finance":null},{"name":"林德福","partyName":"中國國民黨","isElected":true,"rateOfVote":52.43,"finance":{"income":{"total":25041408},"outcome":{"total":13945441}}},{"name":"李幸長","partyName":"無黨籍及未經政黨推薦","isElected":false,"rateOfVote":29.56,"finance":null}]},{"name":"第10選區","candidates":[{"name":"盧嘉辰","partyName":"中國國民黨","isElected":false,"rateOfVote":38.46,"finance":null},{"name":"吳琪銘","partyName":"民主進步黨","isElected":true,"rateOfVote":58.5,"finance":{"income":{"total":9963400},"outcome":{"total":10943581}}},{"name":"黃魯光","partyName":"自由台灣黨","isElected":false,"rateOfVote":3.03,"finance":null}]},{"name":"第11選區","candidates":[{"name":"羅明才","partyName":"中國國民黨","isElected":true,"rateOfVote":51,"finance":{"income":{"total":28683969},"outcome":{"total":27548369}}},{"name":"曾柏瑜","partyName":"綠黨社會民主黨聯盟","isElected":false,"rateOfVote":12.2,"finance":null},{"name":"陳永福","partyName":"民主進步黨","isElected":false,"rateOfVote":36.79,"finance":null}]},{"name":"第12選區","candidates":[{"name":"鐘國誌","partyName":"和平鴿聯盟黨","isElected":false,"rateOfVote":1.63,"finance":null},{"name":"李慶華","partyName":"中國國民黨","isElected":false,"rateOfVote":43.71,"finance":null},{"name":"黃國昌","partyName":"時代力量","isElected":true,"rateOfVote":51.51,"finance":{"income":{"total":32986008},"outcome":{"total":22217653}}},{"name":"陳永順","partyName":"信心希望聯盟","isElected":false,"rateOfVote":3.13,"finance":null}]}],"constituency":{"name":"第01選區","candidates":[{"name":"吳育昇","partyName":"中國國民黨","isElected":false,"rateOfVote":40.87,"finance":null},{"name":"蘇通達","partyName":"樹黨","isElected":false,"rateOfVote":2.47,"finance":null},{"name":"洪志成","partyName":"健保免費連線","isElected":false,"rateOfVote":0.66,"finance":null},{"name":"呂孫綾","partyName":"民主進步黨","isElected":true,"rateOfVote":53.27,"finance":{"income":{"total":782640},"outcome":{"total":7740367}}},{"name":"陳立基","partyName":"無黨籍及未經政黨推薦","isElected":false,"rateOfVote":2.35,"finance":null},{"name":"陳筠棻","partyName":"和平鴿聯盟黨","isElected":false,"rateOfVote":0.35,"finance":null}]}}}